browser_history/__init__.py
browser_history/browsers.py
browser_history/cli.py
browser_history/generic.py
browser_history/utils.py
browser_history-0.5.0.dist-info/licenses/LICENSE
browser_history-0.5.0.dist-info/METADATA
browser_history-0.5.0.dist-info/WHEEL
browser_history-0.5.0.dist-info/entry_points.txt
browser_history-0.5.0.dist-info/top_level.txt
browser_history-0.5.0.dist-info/RECORD
