Metadata-Version: 2.4
Name: browser-history
Version: 0.5.0
Summary: A python module to extract browser history
Author-email: Samyak Sarnayak <samyak201@gmail.com>
Maintainer-email: Samyak Sarnayak <samyak201@gmail.com>, Emmanuel Obara <emmanuelobarany@gmail.com>
Project-URL: Homepage, https://github.com/browser-history/browser-history/
Project-URL: Documentation, https://browser-history.readthedocs.io/en/stable/
Project-URL: Repository, https://github.com/browser-history/browser-history.git
Project-URL: Issues, https://github.com/browser-history/browser-history/issues
Project-URL: Changelog, https://github.com/browser-history/browser-history/releases
Keywords: browser,history,browser-history,chrome,firefox,safari
Classifier: Development Status :: 4 - Beta
Classifier: Programming Language :: Python :: 3
Classifier: License :: OSI Approved :: Apache Software License
Classifier: Operating System :: OS Independent
Requires-Python: >=3.6
License-File: LICENSE
Provides-Extra: dev
Requires-Dist: black~=24.4.0; extra == "dev"
Requires-Dist: build~=1.2.1; extra == "dev"
Requires-Dist: flake8-comprehensions~=3.14.0; extra == "dev"
Requires-Dist: flake8~=7.0.0; extra == "dev"
Requires-Dist: pre-commit~=3.5.0; extra == "dev"
Requires-Dist: pytest-cov~=5.0.0; extra == "dev"
Requires-Dist: pytest~=8.1.1; extra == "dev"
Requires-Dist: python-dateutil~=2.9.0; extra == "dev"
Requires-Dist: twine~=5.0.0; extra == "dev"
Provides-Extra: docs
Requires-Dist: Sphinx==7.3.7; extra == "docs"
Requires-Dist: sphinx-argparse==0.4.0; extra == "docs"
Requires-Dist: sphinx-autodoc-typehints==2.1.0; extra == "docs"
Requires-Dist: sphinx-rtd-theme==2.0.0; extra == "docs"
Dynamic: license-file
